odoo8_addon_stock_inventory_hierarchical_exhaustive-8.0.1.0.0-py2.7-nspkg.pth
odoo8_addon_stock_inventory_hierarchical_exhaustive-8.0.1.0.0.dist-info/DESCRIPTION.rst
odoo8_addon_stock_inventory_hierarchical_exhaustive-8.0.1.0.0.dist-info/METADATA
odoo8_addon_stock_inventory_hierarchical_exhaustive-8.0.1.0.0.dist-info/RECORD
odoo8_addon_stock_inventory_hierarchical_exhaustive-8.0.1.0.0.dist-info/WHEEL
odoo8_addon_stock_inventory_hierarchical_exhaustive-8.0.1.0.0.dist-info/metadata.json
odoo8_addon_stock_inventory_hierarchical_exhaustive-8.0.1.0.0.dist-info/namespace_packages.txt
odoo8_addon_stock_inventory_hierarchical_exhaustive-8.0.1.0.0.dist-info/top_level.txt
odoo_addons/stock_inventory_hierarchical_exhaustive/README.rst
odoo_addons/stock_inventory_hierarchical_exhaustive/__init__.py
odoo_addons/stock_inventory_hierarchical_exhaustive/__openerp__.py
odoo_addons/stock_inventory_hierarchical_exhaustive/i18n/fr.po
odoo_addons/stock_inventory_hierarchical_exhaustive/models/__init__.py
odoo_addons/stock_inventory_hierarchical_exhaustive/models/stock_inventory.py
odoo_addons/stock_inventory_hierarchical_exhaustive/static/src/img/icon.png
odoo_addons/stock_inventory_hierarchical_exhaustive/tests/__init__.py
odoo_addons/stock_inventory_hierarchical_exhaustive/tests/test_stock_inventory_hierarchical_exhaustive.py
odoo_addons/stock_inventory_hierarchical_exhaustive/views/stock_inventory_view.xml
odoo_addons/stock_inventory_hierarchical_exhaustive/wizard/__init__.py
odoo_addons/stock_inventory_hierarchical_exhaustive/wizard/generate_inventory.py
odoo_addons/stock_inventory_hierarchical_exhaustive/wizard/generate_inventory_view.xml
