Metadata-Version: 2.0
Name: odoo8-addon-stock-inventory-hierarchical-exhaustive
Version: 8.0.1.0.0
Summary: Extra consistency checks
Home-page: UNKNOWN
Author: Numérigraphe,Odoo Community Association (OCA)
Author-email: support@odoo-community.org
License: AGPL-3
Platform: UNKNOWN
Classifier: Programming Language :: Python
Classifier: Framework :: Odoo
Classifier: License :: OSI Approved :: GNU Affero General Public License v3
Requires-Python: ~=2.7
Requires-Dist: odoo (<9.0a,>=8.0a)
Requires-Dist: odoo8-addon-stock-inventory-exhaustive
Requires-Dist: odoo8-addon-stock-inventory-hierarchical
